libpythonpro_fer/__init__.py
libpythonpro_fer/github_api.py
libpythonpro_fer/spam/__init__.py
libpythonpro_fer/spam/db.py
libpythonpro_fer/spam/enviador_de_email.py
libpythonpro_fer/spam/main.py
libpythonpro_fer/spam/modelos.py
libpythonpro_fer/tests/__init__.py
libpythonpro_fer/tests/test_exemplo.py
libpythonpro_fer/tests/test_spam/__init__.py
libpythonpro_fer/tests/test_spam/conftest.py
libpythonpro_fer/tests/test_spam/test_enviador_de_email.py
libpythonpro_fer/tests/test_spam/test_envio_para_base_de_usuarios.py
libpythonpro_fer/tests/test_spam/test_github_api.py
libpythonpro_fer/tests/test_spam/test_usuarios.py
libpythonpro_fer-0.2.dist-info/LICENSE
libpythonpro_fer-0.2.dist-info/METADATA
libpythonpro_fer-0.2.dist-info/WHEEL
libpythonpro_fer-0.2.dist-info/top_level.txt
libpythonpro_fer-0.2.dist-info/RECORD
